{
  "architecture": [
    31,
    31,
    31,
    31,
    31,
    31,
    31,
    31,
    31,
    31
  ],
  "batch_size": 8256,
  "command": [
    "/home/anurag/Projects/Breaking-the-Neural-Barrier/.venv/bin/python",
    "/home/anurag/Projects/Breaking-the-Neural-Barrier/MLPS/tabular/shared/dae_dnn/run_stl_ablation.py",
    "--data-dir",
    "./data",
    "--results-dir",
    "MLPS/tabular/shared/dae_dnn/results",
    "--run-root",
    "MLPS/tabular/shared/dae_dnn/results/stl/ablation/parammatched_decade_v1_param_10pow04_06/prediction/_children/stl_ablation_r01_d10_w0031_31_31_31_31_31_31_31_31_31_31",
    "--source-run-root",
    "MLPS/tabular/shared/dae_dnn/results/goliath_w2d_staged_current",
    "--tasks",
    "prediction",
    "--architecture",
    "31,31,31,31,31,31,31,31,31,31",
    "--repeat-count",
    "5",
    "--batch-size",
    "8256",
    "--num-workers",
    "0",
    "--seed",
    "0",
    "--patience",
    "10",
    "--delta",
    "0.0001",
    "--max-epochs",
    "100000000",
    "--lr",
    "0.001",
    "--weight-decay",
    "0.0001",
    "--grad-clip",
    "1.0",
    "--max-width",
    "10000000000",
    "--max-depth",
    "10",
    "--max-neurons",
    "10000000000",
    "--width-stage-margin-patience",
    "10",
    "--width-stage-min-improve-pct",
    "1.0",
    "--min-width",
    "1",
    "--width-step",
    "1",
    "--width-count-per-depth",
    "10",
    "--min-depth",
    "1",
    "--stl-width",
    "128",
    "--stl-depth",
    "2",
    "--metrics-every",
    "0",
    "--device",
    "cpu",
    "--param-band",
    "4",
    "6"
  ],
  "completed": true,
  "completed_at": 1782042019.7876785,
  "failed": false,
  "failure_count": 0,
  "last_started_at": 1781977428.9317544,
  "launch_count": 18,
  "parameter_count": 9859,
  "pause_count": 0,
  "pause_requested": false,
  "phase_name": "stl_ablation_r01_d10_w0031_31_31_31_31_31_31_31_31_31_31",
  "status": "completed",
  "task": "prediction"
}